{"version": "4.6.0", "flags": {}, "shapes": [{"label": "gluewidth", "points": [[354.0, 320.0], [354.0, 331.0], [387.0, 330.0], [387.0, 320.0]]}, {"label": "0", "points": [[125.0, 20.0], [150.0, 20.0], [150.0, 90.0], [125.0, 90.0]]}, {"label": "1", "points": [[384.0, 18.0], [398.0, 18.0], [398.0, 81.0], [384.0, 81.0]]}, {"label": "2", "points": [[454.0, 32.0], [562.0, 32.0], [562.0, 34.0], [454.0, 34.0]]}, {"label": "3", "points": [[641.0, 21.0], [667.0, 21.0], [667.0, 36.0], [641.0, 36.0]]}, {"label": "4", "points": [[810.0, 36.0], [849.0, 36.0], [849.0, 61.0], [810.0, 61.0]]}, {"label": "5", "points": [[144.0, 115.0], [150.0, 115.0], [150.0, 178.0], [144.0, 178.0]]}, {"label": "6", "points": [[276.0, 128.0], [384.0, 128.0], [384.0, 153.0], [276.0, 153.0]]}, {"label": "7", "points": [[443.0, 137.0], [531.0, 137.0], [531.0, 151.0], [443.0, 151.0]]}, {"label": "8", "points": [[638.0, 144.0], [742.0, 144.0], [742.0, 179.0], [638.0, 179.0]]}, {"label": "9", "points": [[805.0, 159.0], [844.0, 159.0], [844.0, 187.0], [805.0, 187.0]]}, {"label": "10", "points": [[101.0, 225.0], [166.0, 225.0], [166.0, 295.0], [101.0, 295.0]]}, {"label": "11", "points": [[256.0, 227.0], [269.0, 227.0], [269.0, 304.0], [256.0, 304.0]]}, {"label": "12", "points": [[440.0, 243.0], [528.0, 243.0], [528.0, 258.0], [440.0, 258.0]]}, {"label": "13", "points": [[634.0, 239.0], [738.0, 239.0], [738.0, 254.0], [634.0, 254.0]]}, {"label": "14", "points": [[841.0, 264.0], [843.0, 264.0], [843.0, 294.0], [841.0, 294.0]]}, {"label": "15", "points": [[99.0, 333.0], [164.0, 333.0], [164.0, 397.0], [99.0, 397.0]]}, {"label": "16", "points": [[93.0, 444.0], [158.0, 444.0], [158.0, 508.0], [93.0, 508.0]]}, {"label": "17", "points": [[254.0, 331.0], [267.0, 331.0], [267.0, 408.0], [254.0, 408.0]]}, {"label": "18", "points": [[254.0, 444.0], [267.0, 444.0], [267.0, 521.0], [254.0, 521.0]]}, {"label": "19", "points": [[440.0, 345.0], [528.0, 345.0], [528.0, 360.0], [440.0, 360.0]]}, {"label": "20", "points": [[458.0, 458.0], [548.0, 458.0], [548.0, 473.0], [458.0, 473.0]]}, {"label": "21", "points": [[635.0, 344.0], [739.0, 344.0], [739.0, 359.0], [635.0, 359.0]]}, {"label": "22", "points": [[641.0, 453.0], [744.0, 453.0], [744.0, 467.0], [641.0, 467.0]]}, {"label": "23", "points": [[843.0, 399.0], [845.0, 399.0], [845.0, 410.0], [843.0, 410.0]]}, {"label": "24", "points": [[848.0, 509.0], [850.0, 509.0], [850.0, 520.0], [848.0, 520.0]]}]}